{
  "entityType" : "NOTIFICATION_TEMPLATE",
  "entity" : {
    "configuration" : {
      "attachReport" : false,
      "deliveryMethodsTemplates" : {
        "WEB" : {
          "method" : "WEB",
          "additionalConfig" : {
            "icon" : {
              "enabled" : false
            },
            "actionButtonConfig" : {
              "enabled" : false
            }
          },
          "body" : "Maintenance work is scheduled for tomorrow (7:00 a.m. - 9:00 a.m. UTC)",
          "enabled" : true,
          "subject" : "Infrastructure maintenance"
        }
      },
      "reportTemplateId" : null,
      "timezone" : null,
      "userId" : null
    },
    "externalId" : {
      "entityType" : "NOTIFICATION_TEMPLATE",
      "id" : "7a2c7870-3b07-11f0-9464-dd129eb04c6d"
    },
    "id" : {
      "entityType" : "NOTIFICATION_TEMPLATE",
      "id" : "7a2c7870-3b07-11f0-9464-dd129eb04c6d"
    },
    "name" : "Maintenance work notification",
    "notificationType" : "GENERAL"
  }
}